README
setup.py
pitest/__init__.py
pitest/__main__.py
pitest/args.py
pitest/case.py
pitest/dag.py
pitest/discover.py
pitest/main.py
pitest/result.py
pitest/runner.py
pitest/scheduler.py
pitest/suite.py
pitest.egg-info/PKG-INFO
pitest.egg-info/SOURCES.txt
pitest.egg-info/dependency_links.txt
pitest.egg-info/top_level.txt