Metadata-Version: 1.1
Name: pitest
Version: 0.1
Summary: An Object Oriented Testing Framework.
Home-page: https://github.com/qzmfranklin/pitest
Author: Zhongming Qu
Author-email: qzmfranklin@gmail.com
License: ['GPL3', 'LGPL']
Keywords: test,unittest
Platform: UNKNOWN
Classifier: Programming Language :: Python :: 3
Classifier: Intended Audience :: Developers
Classifier: License :: OSI Approved :: GNU Library or Lesser General Public License (LGPL)
Classifier: Operating System :: OS Independent
